wireflow/__init__.py
wireflow/dependency.py
wireflow/provider.py
wireflow-0.1.0.dist-info/LICENSE
wireflow-0.1.0.dist-info/METADATA
wireflow-0.1.0.dist-info/WHEEL
wireflow-0.1.0.dist-info/RECORD
