Metadata-Version: 2.1
Name: wireflow
Version: 0.1.0
Summary: A simple dependency injection library that allows you to provide and resolve dependencies.
Home-page: https://github.com/lvlcn-t/wireflow
License: MIT
Keywords: dependency-injection,DI,dependency-injection-container,dependency-injection-framework,dependency-injection-library,dependency-injection-python,dependency-injection-python-library,dependency-injection-python-framework,dependency-injection-python-container
Author: lvlcn-t
Author-email: 75443136+lvlcn-t@users.noreply.github.com
Requires-Python: >=3.11,<4.0
Classifier: Development Status :: 1 - Planning
Classifier: Intended Audience :: Developers
Classifier: License :: OSI Approved :: MIT License
Classifier: Programming Language :: Python :: 3
Classifier: Programming Language :: Python :: 3.11
Classifier: Programming Language :: Python :: 3.12
Project-URL: Repository, https://github.com/lvlcn-t/wireflow
Project-URL: Release Notes, https://github.com/lvlcn-t/wireflow/releases
Project-URL: Source Code, https://github.com/lvlcn-t/wireflow
